odoo/addons/l10n_us_gaap_mis_report/README.rst
odoo/addons/l10n_us_gaap_mis_report/__init__.py
odoo/addons/l10n_us_gaap_mis_report/__manifest__.py
odoo/addons/l10n_us_gaap_mis_report/data/mis_report_balance_sheet.xml
odoo/addons/l10n_us_gaap_mis_report/data/mis_report_income_statement.xml
odoo/addons/l10n_us_gaap_mis_report/data/mis_report_styles.xml
odoo/addons/l10n_us_gaap_mis_report/docs/l10n_us_gaap_balance_sheet.ods
odoo/addons/l10n_us_gaap_mis_report/docs/l10n_us_gaap_income_statement.ods
odoo/addons/l10n_us_gaap_mis_report/static/description/icon.png
odoo11_addon_l10n_us_gaap_mis_report-11.0.1.0.0.dist-info/DESCRIPTION.rst
odoo11_addon_l10n_us_gaap_mis_report-11.0.1.0.0.dist-info/METADATA
odoo11_addon_l10n_us_gaap_mis_report-11.0.1.0.0.dist-info/RECORD
odoo11_addon_l10n_us_gaap_mis_report-11.0.1.0.0.dist-info/WHEEL
odoo11_addon_l10n_us_gaap_mis_report-11.0.1.0.0.dist-info/metadata.json
odoo11_addon_l10n_us_gaap_mis_report-11.0.1.0.0.dist-info/top_level.txt
